onedrive/__init__.py
onedrive/sharepoint.py
onedrive-0.0.14.dist-info/LICENSE
onedrive-0.0.14.dist-info/METADATA
onedrive-0.0.14.dist-info/WHEEL
onedrive-0.0.14.dist-info/top_level.txt
onedrive-0.0.14.dist-info/RECORD
