Metadata-Version: 2.1
Name: onedrive
Version: 0.0.14
Summary: Download shared folders with Selenium in bulk.
Home-page: https://github.com/foxe6/onedrive
Author: f̣ộx̣ệ6
Author-email: foxe6@protonmail.com
License: AGPL-3.0
Keywords: onedrive sharepoint downloader bulk
Platform: UNKNOWN
Classifier: Programming Language :: Python :: 3.7
Classifier: Topic :: Utilities
Classifier: Natural Language :: English
Classifier: Intended Audience :: Developers
Classifier: License :: OSI Approved :: GNU Affero General Public License v3
Classifier: Operating System :: Microsoft :: Windows :: Windows 10
Requires-Python: >=3.7
Requires-Dist: selenium (==3.141.0)
Requires-Dist: omnitools (>=0.0.1)
